Chapter_3/Half_Adder.sv
module Half_Adder(
	input logic A, B, 
	output logic S, C);

         assign S = A ^ B;
         assign C = A & B;
endmodule

Chapter_3/Full_Adder.sv
module Full_Adder(
	input logic A, B, Cin, 
	output logic S, Cout);

	  logic ha0_S, ha0_C, ha1_C;
  	  assign Cout= ha0_C | ha1_C;

  	Half_Adder HA0(.A(A), .B(B), .S(ha0_S), .C(ha0_C));
  	Half_Adder HA1(.A(ha0_S), .B(Cin), .S(S), .C(ha1_C));
endmodule

Chapter_3/adder4_2.sv
module ADDER4_2(
	input logic [3:0] A, B, 
	input logic Cin, 
	output logic [3:0] S, 
	output logic Cout);

	logic C1, C2, C3;

  	Full_Adder FA0(.A(A[0]), .B(B[0]), .Cin(Cin), .S(S[0]), .Cout(C1)); 		// bit 0
  	Full_Adder FA1(.A(A[1]), .B(B[1]), .Cin(C1), .S(S[1]), .Cout(C2)); 		// bit 1
  	Full_Adder FA2(.A(A[2]), .B(B[2]), .Cin(C2), .S(S[2]), .Cout(C3)); 		// bit 2
  	Full_Adder FA3(.A(A[3]), .B(B[3]), .Cin(C3), .S(S[3]), .Cout(Cout)); 		// bit 3
endmodule

Chapter_3/Fig3_14_vcd.sv
`timescale 1ns / 100ps
`default_nettype none

module Fig3_14();
  logic  [3:0] A, B, S;
  logic  Cin, Cout;

 ADDER4_2 adder4(
 .A(A),
 .B(B), 
 .Cin(Cin),
 .S(S),
 .Cout(Cout)
 );
 

  initial begin $dumpfile("Fig3_14.vcd");$dumpvars;
    $monitor("time=%3d, A=%4b, B=%4b, Cin=%1b, S=%4b, Cout=%1b \n", $time, A, B, Cin, S, Cout);

     A = 4'b0000;
	  B = 4'b0000;
	  Cin = 1'b0;


#10
     A = 4'b0001;
	  B = 4'b0001;
	  Cin = 1'b0;
#10
     A = 4'b0011;
	  B = 4'b0001;
	  Cin = 1'b0;
#10
     A = 4'b0011;
	  B = 4'b0011;
	  Cin = 1'b0; 
#10
     A = 4'b0111;
	  B = 4'b0011;
	  Cin = 1'b0; 
#10
     A = 4'b0111;
	  B = 4'b0111;
	  Cin = 1'b0; 
#10
     A = 4'b1111;
	  B = 4'b1111;
	  Cin = 1'b0; 
#10
	  A = 4'b0000;
	  B = 4'b0000;
	  Cin = 1'b1;
#10
     A = 4'b0001;
	  B = 4'b0001;
	  Cin = 1'b1;
#10
     A = 4'b0011;
	  B = 4'b0001;
	  Cin = 1'b1;
#10
     A = 4'b0011;
	  B = 4'b0011;
	  Cin = 1'b1; 
#10
     A = 4'b0111;
	  B = 4'b0011;
	  Cin = 1'b1; 
#10
     A = 4'b0111;
	  B = 4'b0111;
	  Cin = 1'b1; 
#10
     A = 4'b1111;
	  B = 4'b1111;
	  Cin = 1'b1; 
	  
#10	 
    $display("################# end of checking module popcount ###############");
    $finish;
  end
endmodule

`default_nettype wire

Chapter_3/Fig3_14.vcd
$date
    Oct  3, 2023  22:08:51
$end
$version
    TOOL:	xmsim	20.09-s011
$end
$timescale
    100 ps
$end

$scope module Fig3_14 $end
$var reg       4 !    A [3:0] $end
$var reg       4 "    B [3:0] $end
$var reg       4 #    S [3:0] $end
$var reg       1 $    Cin $end
$var reg       1 %    Cout $end

$scope module adder4 $end
$var wire      1 &    A [3] $end
$var wire      1 '    A [2] $end
$var wire      1 (    A [1] $end
$var wire      1 )    A [0] $end
$var wire      1 *    B [3] $end
$var wire      1 +    B [2] $end
$var wire      1 ,    B [1] $end
$var wire      1 -    B [0] $end
$var wire      1 .    Cin  $end
$var reg       4 /    S [3:0] $end
$var reg       1 0    Cout $end
$var reg       1 1    C1 $end
$var reg       1 2    C2 $end
$var reg       1 3    C3 $end

$scope module FA0 $end
$var wire      1 )    A  $end
$var wire      1 -    B  $end
$var wire      1 .    Cin  $end
$var reg       1 4    S $end
$var reg       1 5    Cout $end
$var reg       1 6    ha0_S $end
$var reg       1 7    ha0_C $end
$var reg       1 8    ha1_C $end

$scope module HA0 $end
$var wire      1 )    A  $end
$var wire      1 -    B  $end
$var reg       1 9    S $end
$var reg       1 :    C $end
$upscope $end


$scope module HA1 $end
$var wire      1 ;    A  $end
$var wire      1 .    B  $end
$var reg       1 <    S $end
$var reg       1 =    C $end
$upscope $end

$upscope $end


$scope module FA1 $end
$var wire      1 (    A  $end
$var wire      1 ,    B  $end
$var wire      1 >    Cin  $end
$var reg       1 ?    S $end
$var reg       1 @    Cout $end
$var reg       1 A    ha0_S $end
$var reg       1 B    ha0_C $end
$var reg       1 C    ha1_C $end

$scope module HA0 $end
$var wire      1 (    A  $end
$var wire      1 ,    B  $end
$var reg       1 D    S $end
$var reg       1 E    C $end
$upscope $end


$scope module HA1 $end
$var wire      1 F    A  $end
$var wire      1 >    B  $end
$var reg       1 G    S $end
$var reg       1 H    C $end
$upscope $end

$upscope $end


$scope module FA2 $end
$var wire      1 '    A  $end
$var wire      1 +    B  $end
$var wire      1 I    Cin  $end
$var reg       1 J    S $end
$var reg       1 K    Cout $end
$var reg       1 L    ha0_S $end
$var reg       1 M    ha0_C $end
$var reg       1 N    ha1_C $end

$scope module HA0 $end
$var wire      1 '    A  $end
$var wire      1 +    B  $end
$var reg       1 O    S $end
$var reg       1 P    C $end
$upscope $end


$scope module HA1 $end
$var wire      1 Q    A  $end
$var wire      1 I    B  $end
$var reg       1 R    S $end
$var reg       1 S    C $end
$upscope $end

$upscope $end


$scope module FA3 $end
$var wire      1 &    A  $end
$var wire      1 *    B  $end
$var wire      1 T    Cin  $end
$var reg       1 U    S $end
$var reg       1 V    Cout $end
$var reg       1 W    ha0_S $end
$var reg       1 X    ha0_C $end
$var reg       1 Y    ha1_C $end

$scope module HA0 $end
$var wire      1 &    A  $end
$var wire      1 *    B  $end
$var reg       1 Z    S $end
$var reg       1 [    C $end
$upscope $end


$scope module HA1 $end
$var wire      1 \    A  $end
$var wire      1 T    B  $end
$var reg       1 ]    S $end
$var reg       1 ^    C $end
$upscope $end

$upscope $end

$upscope $end

$upscope $end

$enddefinitions $end
$dumpvars
b0 !
b0 "
b0 #
0$
0%
0&
0'
0(
0)
0*
0+
0,
0-
0.
b0 /
00
01
02
03
04
05
06
07
08
09
0:
0;
0<
0=
0>
0?
0@
0A
0B
0C
0D
0E
0F
0G
0H
0I
0J
0K
0L
0M
0N
0O
0P
0Q
0R
0S
0T
0U
0V
0W
0X
0Y
0Z
0[
0\
0]
0^
$end
#100
b1 !
b1 "
1-
1)
1:
17
15
11
1>
1G
1?
b10 /
b10 #
#200
b11 !
1(
1D
1A
1F
0G
1H
1C
0?
1@
12
b0 /
1I
1R
b0 #
1J
b100 /
b100 #
#300
b11 "
1,
0D
1E
1B
0A
0F
1G
0H
0C
1?
b110 /
b110 #
#400
b111 !
1'
1O
1L
1Q
0R
1S
1N
0J
1K
13
b10 /
1T
1]
b10 #
1U
b1010 /
b1010 #
#500
b111 "
1+
0O
1P
1M
0L
0Q
1R
0S
0N
1J
b1110 /
b1110 #
#600
b1111 !
b1111 "
1*
1&
1[
1X
1V
10
1%
#700
b0 !
b0 "
1$
1.
0*
0+
0,
0-
0&
0'
0(
0)
1<
0[
0P
0E
0:
07
0B
0M
0X
14
05
0@
0K
0V
00
03
02
01
b1111 /
0>
0I
0T
0G
0R
0]
b1111 #
0%
0U
0J
0?
b1101 /
b1001 /
b1 /
b1 #
#800
b1 !
b1 "
1-
1)
1:
17
15
11
1>
1G
1?
b11 /
b11 #
#900
b11 !
1(
1D
1A
1F
0G
1H
1C
0?
1@
12
b1 /
1I
1R
b1 #
1J
b101 /
b101 #
#1000
b11 "
1,
0D
1E
1B
0A
0F
1G
0H
0C
1?
b111 /
b111 #
#1100
b111 !
1'
1O
1L
1Q
0R
1S
1N
0J
1K
13
b11 /
1T
1]
b11 #
1U
b1011 /
b1011 #
#1200
b111 "
1+
0O
1P
1M
0L
0Q
1R
0S
0N
1J
b1111 /
b1111 #
#1300
b1111 !
b1111 "
1*
1&
1[
1X
1V
10
1%
